rite/__init__.py
rite/__main__.py
rite/__version__.py
rite/cli.py
rite/collections/__init__.py
rite/collections/buffer/__init__.py
rite/collections/buffer/bounded_buffer.py
rite/collections/buffer/circular_buffer.py
rite/collections/buffer/ring_buffer.py
rite/collections/buffer/sliding_window.py
rite/collections/cache/__init__.py
rite/collections/cache/lfu_cache.py
rite/collections/cache/lru_cache.py
rite/collections/cache/ttl_cache.py
rite/collections/dict/__init__.py
rite/collections/dict/dict_deep_get.py
rite/collections/dict/dict_deep_set.py
rite/collections/dict/dict_filter.py
rite/collections/dict/dict_invert.py
rite/collections/dict/dict_merge.py
rite/collections/list/__init__.py
rite/collections/list/list_chunk.py
rite/collections/list/list_flatten.py
rite/collections/list/list_group_by.py
rite/collections/list/list_interleave.py
rite/collections/list/list_partition.py
rite/collections/list/list_unique.py
rite/collections/pattern/__init__.py
rite/collections/pattern/object_pool.py
rite/collections/pattern/observer.py
rite/collections/pattern/singleton.py
rite/collections/queue/__init__.py
rite/collections/queue/circular_queue.py
rite/collections/queue/deque_wrapper.py
rite/collections/queue/priority_queue.py
rite/collections/set/__init__.py
rite/collections/tree/__init__.py
rite/collections/tree/binary_tree_node.py
rite/collections/tree/nested_set.py
rite/collections/tree/tree_node.py
rite/collections/tree/trie.py
rite/conversion/__init__.py
rite/conversion/formats/__init__.py
rite/conversion/formats/formats_base64_decode.py
rite/conversion/formats/formats_base64_encode.py
rite/conversion/formats/formats_hex_decode.py
rite/conversion/formats/formats_hex_encode.py
rite/conversion/formats/formats_json_decode.py
rite/conversion/formats/formats_json_encode.py
rite/conversion/formats/formats_url_decode.py
rite/conversion/formats/formats_url_encode.py
rite/conversion/is_protected_type.py
rite/conversion/to_bool.py
rite/conversion/to_bytes.py
rite-0.2.4.dist-info/METADATA
rite-0.2.4.dist-info/WHEEL
rite-0.2.4.dist-info/entry_points.txt
rite-0.2.4.dist-info/licenses/LICENSE
rite-0.2.4.dist-info/RECORD
