Metadata-Version: 2.4
Name: rite
Version: 0.2.4
Summary: Python Utility Package
License: MIT
License-File: LICENSE
Keywords: rite
Author: Scape Agency
Author-email: info@scape.agency
Requires-Python: >=3.12,<4.0
Classifier: Development Status :: 3 - Alpha
Classifier: Intended Audience :: Developers
Classifier: License :: OSI Approved :: MIT License
Classifier: Programming Language :: Python :: 3
Classifier: Programming Language :: Python :: 3.12
Classifier: Programming Language :: Python :: 3.13
Classifier: Programming Language :: Python :: 3.14
Classifier: Topic :: Software Development :: Libraries :: Python Modules
Classifier: Typing :: Typed
Requires-Dist: tzdata (>=2024.1) ; sys_platform == "win32"
Project-URL: Documentation, https://github.com/scape-agency/rite/docs
Project-URL: Homepage, https://www.pyrites.dev
Project-URL: Repository, https://github.com/scape-agency/rite
